{
  "request": {
    "lang": "en",
    "currency": "USD",
    "time": 4,
    "id": 1551215236680,
    "server": "production",
    "host": "iatacodes.org",
    "pid": 40699,
    "key": {
      "id": 14844,
      "api_key": "ee578ab6-2132-41ff-a311-c3b152941942",
      "type": "free",
      "trial_price": null,
      "expired": null,
      "registered": "2019-02-26T19:55:53.000Z",
      "limits_by_hour": 2500,
      "limits_by_minute": 250,
      "demo_methods": [],
      "usage_by_hour": 4,
      "usage_by_minute": 2
    },
    "params": { "lang": "en" },
    "version": 6,
    "method": "aircrafts",
    "client": {
      "country_code": "GB",
      "country": "United Kingdom",
      "city": "Londonderry",
      "lat": 55,
      "lng": -7.3333,
      "ip": "2.100.75.197",
      "device": { "type": "desktop" },
      "agent": {
        "browser": "Chrome",
        "version": "71.0.3578.98",
        "os": "OS X",
        "platform": "Apple Mac"
      }
    }
  },
  "response": [
    {
      "code": "100",
      "name": "Fokker 100",
      "updated": "2015-10-05T20:27:42.000Z"
    },
    {
      "code": "141",
      "name": "British Aerospace BAe 146-100",
      "updated": "2015-10-05T20:27:42.000Z"
    },
    {
      "code": "142",
      "name": "British Aerospace BAe 146-200",
      "updated": "2015-10-05T20:27:42.000Z"
    },
    {
      "code": "143",
      "name": "British Aerospace BAe 146-300",
      "updated": "2015-10-05T20:27:42.000Z"
    },
    {
      "code": "146",
      "name": "British Aerospace BAe 146",
      "updated": "2015-10-05T20:27:42.000Z"
    },
    {
      "code": "14F",
      "name": "British Aerospace BAe 146 Freighter",
      "updated": "2015-10-05T20:27:42.000Z"
    },
    {
      "code": "14X",
      "name": "British Aerospace BAe 146-100QT/QC",
      "updated": "2015-10-05T20:27:42.000Z"
    },
    {
      "code": "14Y",
      "name": "British Aerospace BAe 146-200QT/QC",
      "updated": "2015-10-05T20:27:42.000Z"
    },
    {
      "code": "14Z",
      "name": "British Aerospace BAe 146-300QT/QC",
      "updated": "2015-10-05T20:27:42.000Z"
    },
    {
      "code": "310",
      "name": "Airbus Industrie A310",
      "updated": "2015-10-05T20:27:42.000Z"
    },
    {
      "code": "312",
      "name": "Airbus Industrie A310-200",
      "updated": "2015-10-05T20:27:42.000Z"
    },
    {
      "code": "313",
      "name": "Airbus Industrie A310-300",
      "updated": "2015-10-05T20:27:42.000Z"
    },
    {
      "code": "318",
      "name": "Airbus Industrie A318",
      "updated": "2015-10-05T20:27:42.000Z"
    },
    {
      "code": "319",
      "name": "Airbus Industrie A319",
      "updated": "2015-10-05T20:27:42.000Z"
    },
    {
      "code": "31F",
      "name": "Airbus Industrie A310 Freighter",
      "updated": "2015-10-05T20:27:42.000Z"
    },
    {
      "code": "31X",
      "name": "Airbus Industrie A310-200 Freighter",
      "updated": "2015-10-05T20:27:42.000Z"
    },
    {
      "code": "31Y",
      "name": "Airbus Industrie A310-300 Freighter",
      "updated": "2015-10-05T20:27:42.000Z"
    },
    {
      "code": "320",
      "name": "Airbus Industrie A320",
      "updated": "2015-10-05T20:27:42.000Z"
    },
    {
      "code": "321",
      "name": "Airbus Industrie A321",
      "updated": "2015-10-05T20:27:42.000Z"
    },
    {
      "code": "32S",
      "name": "Airbus Industrie A318/319/320/321",
      "updated": "2015-10-05T20:27:42.000Z"
    },
    {
      "code": "330",
      "name": "Airbus Industrie A330",
      "updated": "2015-10-05T20:27:42.000Z"
    },
    {
      "code": "332",
      "name": "Airbus Industrie A330-200",
      "updated": "2015-10-05T20:27:42.000Z"
    },
    {
      "code": "333",
      "name": "Airbus Industrie A330-300",
      "updated": "2015-10-05T20:27:42.000Z"
    },
    {
      "code": "340",
      "name": "Airbus Industrie A340",
      "updated": "2015-10-05T20:27:42.000Z"
    },
    {
      "code": "342",
      "name": "Airbus Industrie A340-200",
      "updated": "2015-10-05T20:27:42.000Z"
    },
    {
      "code": "343",
      "name": "Airbus Industrie A340-300",
      "updated": "2015-10-05T20:27:42.000Z"
    },
    {
      "code": "345",
      "name": "Airbus Industrie A340-500",
      "updated": "2015-10-05T20:27:42.000Z"
    },
    {
      "code": "346",
      "name": "Airbus Industrie A340-600",
      "updated": "2015-10-05T20:27:42.000Z"
    },
    {
      "code": "380",
      "name": "Airbus Industrie A380",
      "updated": "2015-10-05T20:27:42.000Z"
    },
    {
      "code": "388",
      "name": "Airbus Industrie A380-800",
      "updated": "2015-10-05T20:27:42.000Z"
    },
    {
      "code": "38F",
      "name": "Airbus Industrie A380 Freighter",
      "updated": "2015-10-05T20:27:42.000Z"
    },
    {
      "code": "703",
      "name": "Boeing 707-300",
      "updated": "2015-10-05T20:27:42.000Z"
    },
    {
      "code": "707",
      "name": "Boeing 707/720",
      "updated": "2015-10-05T20:27:42.000Z"
    },
    {
      "code": "70F",
      "name": "Boeing 707-300 Freighter",
      "updated": "2015-10-05T20:27:42.000Z"
    },
    {
      "code": "70M",
      "name": "Boeing 707-300 Combi",
      "updated": "2015-10-05T20:27:42.000Z"
    },
    {
      "code": "717",
      "name": "Boeing 717-200",
      "updated": "2015-10-05T20:27:42.000Z"
    },
    {
      "code": "721",
      "name": "Boeing 727-100",
      "updated": "2015-10-05T20:27:42.000Z"
    },
    {
      "code": "722",
      "name": "Boeing 727-200",
      "updated": "2015-10-05T20:27:42.000Z"
    },
    {
      "code": "727",
      "name": "Boeing 727",
      "updated": "2015-10-05T20:27:42.000Z"
    },
    {
      "code": "72A",
      "name": "Boeing 727-200 Advanced",
      "updated": "2015-10-05T20:27:42.000Z"
    },
    {
      "code": "72B",
      "name": "Boeing 727-100 Combi",
      "updated": "2015-10-05T20:27:42.000Z"
    },
    {
      "code": "72C",
      "name": "Boeing 727-200 Combi",
      "updated": "2015-10-05T20:27:42.000Z"
    },
    {
      "code": "72F",
      "name": "Boeing 727 Freighter",
      "updated": "2015-10-05T20:27:42.000Z"
    },
    {
      "code": "72M",
      "name": "Boeing 727 Combi",
      "updated": "2015-10-05T20:27:42.000Z"
    },
    {
      "code": "72S",
      "name": "Boeing 727-200",
      "updated": "2015-10-05T20:27:42.000Z"
    },
    {
      "code": "72X",
      "name": "Boeing 727-100 Freighter",
      "updated": "2015-10-05T20:27:42.000Z"
    },
    {
      "code": "72Y",
      "name": "Boeing 727-200 Freighter",
      "updated": "2015-10-05T20:27:42.000Z"
    },
    {
      "code": "731",
      "name": "Boeing 737-100",
      "updated": "2015-10-05T20:27:42.000Z"
    },
    {
      "code": "732",
      "name": "Boeing 737-200",
      "updated": "2015-10-05T20:27:42.000Z"
    },
    {
      "code": "733",
      "name": "Boeing 737-300",
      "updated": "2015-10-05T20:27:42.000Z"
    },
    {
      "code": "734",
      "name": "Boeing 737-400",
      "updated": "2015-10-05T20:27:42.000Z"
    },
    {
      "code": "735",
      "name": "Boeing 737-500",
      "updated": "2015-10-05T20:27:42.000Z"
    },
    {
      "code": "736",
      "name": "Boeing 737-600",
      "updated": "2015-10-05T20:27:42.000Z"
    },
    {
      "code": "737",
      "name": "Boeing 737",
      "updated": "2015-10-05T20:27:42.000Z"
    },
    {
      "code": "738",
      "name": "Boeing 737-800",
      "updated": "2015-10-05T20:27:42.000Z"
    },
    {
      "code": "739",
      "name": "Boeing 737-900",
      "updated": "2015-10-05T20:27:42.000Z"
    },
    {
      "code": "73A",
      "name": "Boeing 737-200/200C Advanced",
      "updated": "2015-10-05T20:27:42.000Z"
    },
    {
      "code": "73C",
      "name": "Boeing 737-300",
      "updated": "2015-10-05T20:27:42.000Z"
    },
    {
      "code": "73E",
      "name": "Boeing 737-900ER",
      "updated": "2015-10-05T20:27:42.000Z"
    },
    {
      "code": "73F",
      "name": "Boeing 737 Freighter",
      "updated": "2015-10-05T20:27:42.000Z"
    },
    {
      "code": "73G",
      "name": "Boeing 737-700",
      "updated": "2015-10-05T20:27:42.000Z"
    },
    {
      "code": "73H",
      "name": "Boeing 737-800 With Winglets",
      "updated": "2015-10-05T20:27:42.000Z"
    },
    {
      "code": "73J",
      "name": "Boeing 737-900 With Winglets",
      "updated": "2015-10-05T20:27:42.000Z"
    },
    {
      "code": "73M",
      "name": "Boeing 737-200 Combi",
      "updated": "2015-10-05T20:27:42.000Z"
    },
    {
      "code": "73N",
      "name": "Boeing 737-300 Mixed Config",
      "updated": "2015-10-05T20:27:42.000Z"
    },
    {
      "code": "73P",
      "name": "Boeing 737-400 Freighter",
      "updated": "2015-10-05T20:27:42.000Z"
    },
    {
      "code": "73Q",
      "name": "Boeing 737-400 Mixed Config",
      "updated": "2015-10-05T20:27:42.000Z"
    },
    {
      "code": "73S",
      "name": "Boeing 737 Advanced",
      "updated": "2015-10-05T20:27:42.000Z"
    },
    {
      "code": "73W",
      "name": "Boeing 737-700 With Winglets",
      "updated": "2015-10-05T20:27:42.000Z"
    },
    {
      "code": "73X",
      "name": "Boeing 737-200 Freighter",
      "updated": "2015-10-05T20:27:42.000Z"
    },
    {
      "code": "73Y",
      "name": "Boeing 737-300 Freighter",
      "updated": "2015-10-05T20:27:42.000Z"
    },
    {
      "code": "741",
      "name": "Boeing 747-100",
      "updated": "2015-10-05T20:27:42.000Z"
    },
    {
      "code": "742",
      "name": "Boeing 747-200",
      "updated": "2015-10-05T20:27:42.000Z"
    },
    {
      "code": "743",
      "name": "Boeing 747-300 (including -100SUD and -200SUD)",
      "updated": "2015-10-05T20:27:42.000Z"
    },
    {
      "code": "744",
      "name": "Boeing 747-400",
      "updated": "2015-10-05T20:27:42.000Z"
    },
    {
      "code": "747",
      "name": "Boeing 747",
      "updated": "2015-10-05T20:27:42.000Z"
    },
    {
      "code": "74C",
      "name": "Boeing 747-200 Combi",
      "updated": "2015-10-05T20:27:42.000Z"
    },
    {
      "code": "74D",
      "name": "Boeing 747-300 Combi (including -200SUD)",
      "updated": "2015-10-05T20:27:42.000Z"
    },
    {
      "code": "74E",
      "name": "Boeing 747-400 Combi",
      "updated": "2015-10-05T20:27:42.000Z"
    },
    {
      "code": "74F",
      "name": "Boeing 747 Freighter",
      "updated": "2015-10-05T20:27:42.000Z"
    },
    {
      "code": "74J",
      "name": "Boeing 747-400 Domestic",
      "updated": "2015-10-05T20:27:42.000Z"
    },
    {
      "code": "74L",
      "name": "Boeing 747SP",
      "updated": "2015-10-05T20:27:42.000Z"
    },
    {
      "code": "74M",
      "name": "Boeing 747 Combi",
      "updated": "2015-10-05T20:27:42.000Z"
    },
    {
      "code": "74T",
      "name": "Boeing 747-100 Freighter",
      "updated": "2015-10-05T20:27:42.000Z"
    },
    {
      "code": "74U",
      "name": "Boeing 747-300 Freighter",
      "updated": "2015-10-05T20:27:42.000Z"
    },
    {
      "code": "74V",
      "name": "Boeing 747SR Freighter",
      "updated": "2015-10-05T20:27:42.000Z"
    },
    {
      "code": "74X",
      "name": "Boeing 747-200 Freighter",
      "updated": "2015-10-05T20:27:42.000Z"
    },
    {
      "code": "74Y",
      "name": "Boeing 747-400 Freighter",
      "updated": "2015-10-05T20:27:42.000Z"
    },
    {
      "code": "752",
      "name": "Boeing 757-200",
      "updated": "2015-10-05T20:27:42.000Z"
    },
    {
      "code": "753",
      "name": "Boeing 757-300",
      "updated": "2015-10-05T20:27:42.000Z"
    },
    {
      "code": "757",
      "name": "Boeing 757",
      "updated": "2015-10-05T20:27:42.000Z"
    },
    {
      "code": "75F",
      "name": "Boeing 757-200 Freighter",
      "updated": "2015-10-05T20:27:42.000Z"
    },
    {
      "code": "75M",
      "name": "Boeing 757-200 Combi",
      "updated": "2015-10-05T20:27:42.000Z"
    },
    {
      "code": "75W",
      "name": "Boeing 757-200 With Winglets",
      "updated": "2015-10-05T20:27:42.000Z"
    },
    {
      "code": "762",
      "name": "Boeing 767-200",
      "updated": "2015-10-05T20:27:42.000Z"
    },
    {
      "code": "763",
      "name": "Boeing 767-300",
      "updated": "2015-10-05T20:27:42.000Z"
    },
    {
      "code": "764",
      "name": "Boeing 767-400",
      "updated": "2015-10-05T20:27:42.000Z"
    },
    {
      "code": "767",
      "name": "Boeing 767",
      "updated": "2015-10-05T20:27:42.000Z"
    },
    {
      "code": "76F",
      "name": "Boeing 767 Freighter",
      "updated": "2015-10-05T20:27:42.000Z"
    },
    {
      "code": "76X",
      "name": "Boeing 767-200 Freighter",
      "updated": "2015-10-05T20:27:42.000Z"
    },
    {
      "code": "76Y",
      "name": "Boeing 767-300 Freighter",
      "updated": "2015-10-05T20:27:42.000Z"
    },
    {
      "code": "772",
      "name": "Boeing 777-200/200ER",
      "updated": "2015-10-05T20:27:42.000Z"
    },
    {
      "code": "773",
      "name": "Boeing 777-300",
      "updated": "2015-10-05T20:27:42.000Z"
    },
    {
      "code": "777",
      "name": "Boeing 777",
      "updated": "2015-10-05T20:27:42.000Z"
    },
    {
      "code": "77L",
      "name": "Boeing 777-200LR",
      "updated": "2015-10-05T20:27:42.000Z"
    },
    {
      "code": "77W",
      "name": "Boeing 777-300ER",
      "updated": "2015-10-05T20:27:42.000Z"
    },
    {
      "code": "A26",
      "name": "Antonov An-26",
      "updated": "2015-10-05T20:27:42.000Z"
    },
    {
      "code": "A28",
      "name": "Antonov An-28",
      "updated": "2015-10-05T20:27:42.000Z"
    },
    {
      "code": "A30",
      "name": "Antonov An-30",
      "updated": "2015-10-05T20:27:42.000Z"
    },
    {
      "code": "A32",
      "name": "Antonov An-32",
      "updated": "2015-10-05T20:27:42.000Z"
    },
    {
      "code": "A40",
      "name": "Antonov An-140",
      "updated": "2015-10-05T20:27:42.000Z"
    },
    {
      "code": "A4F",
      "name": "Antonov An-124 Ruslan",
      "updated": "2015-10-05T20:27:42.000Z"
    },
    {
      "code": "A81",
      "name": "Antonov An-148-100",
      "updated": "2015-10-05T20:27:42.000Z"
    },
    {
      "code": "AB3",
      "name": "Airbus Industrie A300",
      "updated": "2015-10-05T20:27:42.000Z"
    },
    {
      "code": "AB4",
      "name": "Airbus Industrie A300B2/B4/C4",
      "updated": "2015-10-05T20:27:42.000Z"
    },
    {
      "code": "AB6",
      "name": "Airbus Industrie A300-600",
      "updated": "2015-10-05T20:27:42.000Z"
    },
    {
      "code": "ABB",
      "name": "Airbus Industrie A300-600ST Beluga",
      "updated": "2015-10-05T20:27:42.000Z"
    },
    {
      "code": "ABF",
      "name": "Airbus Industrie A300 Freighter",
      "updated": "2015-10-05T20:27:42.000Z"
    },
    {
      "code": "ABX",
      "name": "Airbus Industrie A300B4/C4/F4 Freighter",
      "updated": "2015-10-05T20:27:42.000Z"
    },
    {
      "code": "ABY",
      "name": "Airbus Industrie A300-600 Freighter",
      "updated": "2015-10-05T20:27:42.000Z"
    },
    {
      "code": "ACD",
      "name": "Twin Aero Commander/Turbo/Jetprop",
      "updated": "2015-10-05T20:27:42.000Z"
    },
    {
      "code": "AGH",
      "name": "Agusta A109",
      "updated": "2015-10-05T20:27:42.000Z"
    },
    {
      "code": "AN4",
      "name": "Antonov An-24",
      "updated": "2015-10-05T20:27:42.000Z"
    },
    {
      "code": "AN6",
      "name": "Antonov An-26/30/32",
      "updated": "2015-10-05T20:27:42.000Z"
    },
    {
      "code": "AN7",
      "name": "Antonov An-72/74",
      "updated": "2015-10-05T20:27:42.000Z"
    },
    {
      "code": "ANF",
      "name": "Antonov An-12",
      "updated": "2015-10-05T20:27:42.000Z"
    },
    {
      "code": "AR1",
      "name": "Avro RJ100 Avroliner",
      "updated": "2015-10-05T20:27:42.000Z"
    },
    {
      "code": "AR7",
      "name": "Avro RJ70 Avroliner",
      "updated": "2015-10-05T20:27:42.000Z"
    },
    {
      "code": "AR8",
      "name": "Avro RJ85 Avroliner",
      "updated": "2015-10-05T20:27:42.000Z"
    },
    {
      "code": "ARJ",
      "name": "Avro RJ Avroliner",
      "updated": "2015-10-05T20:27:42.000Z"
    },
    {
      "code": "ARX",
      "name": "Avro RJX",
      "updated": "2015-10-05T20:27:42.000Z"
    },
    {
      "code": "AT4",
      "name": "Aerospatiale/Alenia ATR 42-300/320",
      "updated": "2015-10-05T20:27:42.000Z"
    },
    {
      "code": "AT5",
      "name": "Aerospatiale/Alenia ATR 42-500",
      "updated": "2015-10-05T20:27:42.000Z"
    },
    {
      "code": "AT7",
      "name": "Aerospatiale/Alenia ATR 72",
      "updated": "2015-10-05T20:27:42.000Z"
    },
    {
      "code": "ATP",
      "name": "British Aerospace ATP",
      "updated": "2015-10-05T20:27:42.000Z"
    },
    {
      "code": "ATR",
      "name": "Aerospatiale/Alenia ATR",
      "updated": "2015-10-05T20:27:42.000Z"
    },
    {
      "code": "AX1",
      "name": "Avro RJX100",
      "updated": "2015-10-05T20:27:42.000Z"
    },
    {
      "code": "AX8",
      "name": "Avro RJX85",
      "updated": "2015-10-05T20:27:42.000Z"
    },
    {
      "code": "B11",
      "name": "British Aerospace BAC One Eleven",
      "updated": "2015-10-05T20:27:42.000Z"
    },
    {
      "code": "B12",
      "name": "British Aerospace BAC One Eleven 200",
      "updated": "2015-10-05T20:27:42.000Z"
    },
    {
      "code": "B13",
      "name": "British Aerospace BAC One Eleven 300",
      "updated": "2015-10-05T20:27:42.000Z"
    },
    {
      "code": "B14",
      "name": "British Aerospace BAC One Eleven 400",
      "updated": "2015-10-05T20:27:42.000Z"
    },
    {
      "code": "B15",
      "name": "British Aerospace BAC One Eleven 500",
      "updated": "2015-10-05T20:27:42.000Z"
    },
    {
      "code": "B72",
      "name": "Boeing 720B",
      "updated": "2015-10-05T20:27:42.000Z"
    },
    {
      "code": "BE1",
      "name": "Beechcraft Beech 1900",
      "updated": "2015-10-05T20:27:42.000Z"
    },
    {
      "code": "BE2",
      "name": "Beechcraft twin piston",
      "updated": "2015-10-05T20:27:42.000Z"
    },
    {
      "code": "BE9",
      "name": "Beechcraft Airliner 99",
      "updated": "2015-10-05T20:27:42.000Z"
    },
    {
      "code": "BEC",
      "name": "Beechcraft Light Aircraft",
      "updated": "2015-10-05T20:27:42.000Z"
    },
    {
      "code": "BEH",
      "name": "Beechcraft Beech 1900D",
      "updated": "2015-10-05T20:27:42.000Z"
    },
    {
      "code": "BES",
      "name": "Beechcraft Beech 1900C",
      "updated": "2015-10-05T20:27:42.000Z"
    },
    {
      "code": "BET",
      "name": "Beechcraft Light Aircraft Twin Prop",
      "updated": "2015-10-05T20:27:42.000Z"
    },
    {
      "code": "BH2",
      "name": "Bell Helicopters",
      "updated": "2015-10-05T20:27:42.000Z"
    },
    {
      "code": "BNI",
      "name": "Pilatus Britten-Norman BN-2A/B",
      "updated": "2015-10-05T20:27:42.000Z"
    },
    {
      "code": "BNT",
      "name": "Pilatus Britten-Norman BN-2A Trislander",
      "updated": "2015-10-05T20:27:42.000Z"
    },
    {
      "code": "BUS",
      "name": "Non Aircraft - Bus",
      "updated": "2015-10-05T20:27:42.000Z"
    },
    {
      "code": "CCJ",
      "name": "Canadair Challenger",
      "updated": "2015-10-05T20:27:42.000Z"
    },
    {
      "code": "CD2",
      "name": "Government Aircraft Factories N22B/N24A Nomad",
      "updated": "2015-10-05T20:27:42.000Z"
    },
    {
      "code": "CN1",
      "name": "Cessna light aircraft - single piston engine",
      "updated": "2015-10-05T20:27:42.000Z"
    },
    {
      "code": "CNA",
      "name": "Cessna Light Aircraft",
      "updated": "2015-10-05T20:27:42.000Z"
    },
    {
      "code": "CNC",
      "name": "Cessna light aircraft - single turboprop engine",
      "updated": "2015-10-05T20:27:42.000Z"
    },
    {
      "code": "CNJ",
      "name": "Cessna Citation",
      "updated": "2015-10-05T20:27:42.000Z"
    },
    {
      "code": "CNT",
      "name": "Cessna light aircraft - twin turboprop engines",
      "updated": "2015-10-05T20:27:42.000Z"
    },
    {
      "code": "CR1",
      "name": "Canadair Regional Jet 100",
      "updated": "2015-10-05T20:27:42.000Z"
    },
    {
      "code": "CR2",
      "name": "Canadair Regional Jet 200",
      "updated": "2015-10-05T20:27:42.000Z"
    },
    {
      "code": "CR7",
      "name": "Canadair Regional Jet 700",
      "updated": "2015-10-05T20:27:42.000Z"
    },
    {
      "code": "CR9",
      "name": "Canadair Regional Jet 900",
      "updated": "2015-10-05T20:27:42.000Z"
    },
    {
      "code": "CRA",
      "name": "Canadair Regional Jet 705",
      "updated": "2015-10-05T20:27:42.000Z"
    },
    {
      "code": "CRJ",
      "name": "Canadair Regional Jet",
      "updated": "2015-10-05T20:27:42.000Z"
    },
    {
      "code": "CRV",
      "name": "Aerospatiale/SUD SE210 Caravelle",
      "updated": "2015-10-05T20:27:42.000Z"
    },
    {
      "code": "CS2",
      "name": "CASA/IPTN CN-212 Aviocar",
      "updated": "2015-10-05T20:27:42.000Z"
    },
    {
      "code": "CS5",
      "name": "CASA/IPTN CN-235",
      "updated": "2015-10-05T20:27:42.000Z"
    },
    {
      "code": "CV5",
      "name": "Convair 580",
      "updated": "2015-10-05T20:27:42.000Z"
    },
    {
      "code": "CVF",
      "name": "Convair 580/600/640 Freighter",
      "updated": "2015-10-05T20:27:42.000Z"
    },
    {
      "code": "CVR",
      "name": "Convair 240/440/580",
      "updated": "2015-10-05T20:27:42.000Z"
    },
    {
      "code": "CWC",
      "name": "Curtiss C-46 Commando",
      "updated": "2015-10-05T20:27:42.000Z"
    },
    {
      "code": "D10",
      "name": "Boeing/McDonnell Douglas DC-10",
      "updated": "2015-10-05T20:27:42.000Z"
    },
    {
      "code": "D11",
      "name": "Boeing/McDonnell Douglas DC-10-10/15",
      "updated": "2015-10-05T20:27:42.000Z"
    },
    {
      "code": "D1C",
      "name": "Boeing/McDonnell Douglas DC-10-30/40",
      "updated": "2015-10-05T20:27:42.000Z"
    },
    {
      "code": "D1F",
      "name": "Boeing/McDonnell Douglas DC-10 Freighter",
      "updated": "2015-10-05T20:27:42.000Z"
    },
    {
      "code": "D1X",
      "name": "Boeing/McDonnell Douglas DC-10-10 Freighter",
      "updated": "2015-10-05T20:27:42.000Z"
    },
    {
      "code": "D1Y",
      "name": "Boeing/McDonnell Douglas DC-10-30/40 Freighter",
      "updated": "2015-10-05T20:27:42.000Z"
    },
    {
      "code": "D28",
      "name": "Fairchild Dornier Do-228",
      "updated": "2015-10-05T20:27:42.000Z"
    },
    {
      "code": "D38",
      "name": "Fairchild Dornier Do-328",
      "updated": "2015-10-05T20:27:42.000Z"
    },
    {
      "code": "D3F",
      "name": "Boeing/Douglas DC-3 Freighter",
      "updated": "2015-10-05T20:27:42.000Z"
    },
    {
      "code": "D6F",
      "name": "Boeing/Douglas DC-6A/B/C Freighter",
      "updated": "2015-10-05T20:27:42.000Z"
    },
    {
      "code": "D8F",
      "name": "Boeing/McDonnell Douglas DC-8 Freighter",
      "updated": "2015-10-05T20:27:42.000Z"
    },
    {
      "code": "D8L",
      "name": "Boeing/McDonnell Douglas DC-8-62",
      "updated": "2015-10-05T20:27:42.000Z"
    },
    {
      "code": "D8M",
      "name": "Boeing/McDonnell Douglas DC-8 Combi",
      "updated": "2015-10-05T20:27:42.000Z"
    },
    {
      "code": "D8Q",
      "name": "Boeing/McDonnell Douglas DC-8-72",
      "updated": "2015-10-05T20:27:42.000Z"
    },
    {
      "code": "D8T",
      "name": "Boeing/McDonnell Douglas DC-8-50 Freighter",
      "updated": "2015-10-05T20:27:42.000Z"
    },
    {
      "code": "D8X",
      "name": "Boeing/McDonnell Douglas DC-8-61/62/63 Freighter",
      "updated": "2015-10-05T20:27:42.000Z"
    },
    {
      "code": "D8Y",
      "name": "Boeing/McDonnell Douglas DC-8-71/72/73 Freighter",
      "updated": "2015-10-05T20:27:42.000Z"
    },
    {
      "code": "D91",
      "name": "Boeing/McDonnell Douglas DC-9-10",
      "updated": "2015-10-05T20:27:42.000Z"
    },
    {
      "code": "D92",
      "name": "Boeing/McDonnell Douglas DC-9-20",
      "updated": "2015-10-05T20:27:42.000Z"
    },
    {
      "code": "D93",
      "name": "Boeing/McDonnell Douglas DC-9-30",
      "updated": "2015-10-05T20:27:42.000Z"
    },
    {
      "code": "D94",
      "name": "Boeing/McDonnell Douglas DC-9-40",
      "updated": "2015-10-05T20:27:42.000Z"
    },
    {
      "code": "D95",
      "name": "Boeing/McDonnell Douglas DC-9-50",
      "updated": "2015-10-05T20:27:42.000Z"
    },
    {
      "code": "D9C",
      "name": "Boeing/McDonnell Douglas DC-9-30 Freighter",
      "updated": "2015-10-05T20:27:42.000Z"
    },
    {
      "code": "D9F",
      "name": "Boeing/McDonnell Douglas DC-9-40 Freighter",
      "updated": "2015-10-05T20:27:42.000Z"
    },
    {
      "code": "D9S",
      "name": "Boeing/McDonnell Douglas DC-9-30/40/50",
      "updated": "2015-10-05T20:27:42.000Z"
    },
    {
      "code": "D9X",
      "name": "Boeing/McDonnell Douglas DC-9-10 Freighter",
      "updated": "2015-10-05T20:27:42.000Z"
    },
    {
      "code": "DC3",
      "name": "Boeing/Douglas DC-3",
      "updated": "2015-10-05T20:27:42.000Z"
    },
    {
      "code": "DC6",
      "name": "Boeing/Douglas DC-6",
      "updated": "2015-10-05T20:27:42.000Z"
    },
    {
      "code": "DC8",
      "name": "Boeing/McDonnell Douglas DC-8",
      "updated": "2015-10-05T20:27:42.000Z"
    },
    {
      "code": "DC9",
      "name": "Boeing/McDonnell Douglas DC-9",
      "updated": "2015-10-05T20:27:42.000Z"
    },
    {
      "code": "DCF",
      "name": "Boeing/McDonnell Douglas DC-9 Freighter",
      "updated": "2015-10-05T20:27:42.000Z"
    },
    {
      "code": "DH1",
      "name": "De Havilland Canada DHC-8-100 Dash 8/8Q",
      "updated": "2015-10-05T20:27:42.000Z"
    },
    {
      "code": "DH2",
      "name": "De Havilland Canada DHC-8-200 Dash 8/8Q",
      "updated": "2015-10-05T20:27:42.000Z"
    },
    {
      "code": "DH3",
      "name": "De Havilland Canada DHC-8-300 Dash 8/8Q",
      "updated": "2015-10-05T20:27:42.000Z"
    },
    {
      "code": "DH4",
      "name": "De Havilland Canada DHC-8-400 Dash 8/8Q",
      "updated": "2015-10-05T20:27:42.000Z"
    },
    {
      "code": "DH7",
      "name": "De Havilland Canada DHC-7 Dash 7",
      "updated": "2015-10-05T20:27:42.000Z"
    },
    {
      "code": "DH8",
      "name": "De Havilland Canada DHC-8 Dash 8 All S.",
      "updated": "2015-10-05T20:27:42.000Z"
    },
    {
      "code": "DHC",
      "name": "De Havilland Canada DHC-4 Caribou",
      "updated": "2015-10-05T20:27:42.000Z"
    },
    {
      "code": "DHL",
      "name": "De Havilland Canada DHC-3 Turbo Otter",
      "updated": "2015-10-05T20:27:42.000Z"
    },
    {
      "code": "DHP",
      "name": "De Havilland Canada DHC-2 Beaver",
      "updated": "2015-10-05T20:27:42.000Z"
    },
    {
      "code": "DHS",
      "name": "De Havilland Canada DHC-3 Otter",
      "updated": "2015-10-05T20:27:42.000Z"
    },
    {
      "code": "DHT",
      "name": "De Havilland Canada DHC-6 Twin Otter",
      "updated": "2015-10-05T20:27:42.000Z"
    },
    {
      "code": "E70",
      "name": "Embraer ERJ-170",
      "updated": "2015-10-05T20:27:42.000Z"
    },
    {
      "code": "E75",
      "name": "Embraer ERJ-175",
      "updated": "2015-10-05T20:27:42.000Z"
    },
    {
      "code": "E90",
      "name": "Embraer ERJ-190",
      "updated": "2015-10-05T20:27:42.000Z"
    },
    {
      "code": "E95",
      "name": "Embraer ERJ-195",
      "updated": "2015-10-05T20:27:42.000Z"
    },
    {
      "code": "EM2",
      "name": "Embraer EMB-120 Brasilia",
      "updated": "2015-10-05T20:27:42.000Z"
    },
    {
      "code": "EM9",
      "name": "Embraer E190",
      "updated": "2015-10-05T20:27:42.000Z"
    },
    {
      "code": "EMB",
      "name": "Embraer EMB-110 Bandeirante",
      "updated": "2015-10-05T20:27:42.000Z"
    },
    {
      "code": "EMJ",
      "name": "Embraer ERJ-170/190",
      "updated": "2015-10-05T20:27:42.000Z"
    },
    {
      "code": "ER3",
      "name": "Embraer ERJ-135 Regional Jet",
      "updated": "2015-10-05T20:27:42.000Z"
    },
    {
      "code": "ER4",
      "name": "Embraer ERJ-145 Regional Jet",
      "updated": "2015-10-05T20:27:42.000Z"
    },
    {
      "code": "ERD",
      "name": "Embraer ERJ-140 Regional Jet",
      "updated": "2015-10-05T20:27:42.000Z"
    },
    {
      "code": "ERJ",
      "name": "Embraer ERJ-135/140/145 Regional Jet",
      "updated": "2015-10-05T20:27:42.000Z"
    },
    {
      "code": "F21",
      "name": "Fokker F28 Fellowship 1000",
      "updated": "2015-10-05T20:27:42.000Z"
    },
    {
      "code": "F22",
      "name": "Fokker F28 Fellowship 2000",
      "updated": "2015-10-05T20:27:42.000Z"
    },
    {
      "code": "F23",
      "name": "Fokker F28 Fellowship 3000",
      "updated": "2015-10-05T20:27:42.000Z"
    },
    {
      "code": "F24",
      "name": "Fokker F28 Fellowship 4000",
      "updated": "2015-10-05T20:27:42.000Z"
    },
    {
      "code": "F27",
      "name": "Fokker F27 Friendship/Fairchild F27",
      "updated": "2015-10-05T20:27:42.000Z"
    },
    {
      "code": "F28",
      "name": "Fokker F28 Fellowship",
      "updated": "2015-10-05T20:27:42.000Z"
    },
    {
      "code": "F50",
      "name": "Fokker 50",
      "updated": "2015-10-05T20:27:42.000Z"
    },
    {
      "code": "F70",
      "name": "Fokker 70",
      "updated": "2015-10-05T20:27:42.000Z"
    },
    {
      "code": "FA7",
      "name": "Fairchild Dornier 728JET",
      "updated": "2015-10-05T20:27:42.000Z"
    },
    {
      "code": "FK7",
      "name": "Fairchild FH227",
      "updated": "2015-10-05T20:27:42.000Z"
    },
    {
      "code": "FRJ",
      "name": "Fairchild Dornier 328JET",
      "updated": "2015-10-05T20:27:42.000Z"
    },
    {
      "code": "GRG",
      "name": "Grumman G-21 Goose",
      "updated": "2015-10-05T20:27:42.000Z"
    },
    {
      "code": "GRM",
      "name": "Grumman G-73 Turbo Mallard",
      "updated": "2015-10-05T20:27:42.000Z"
    },
    {
      "code": "HEC",
      "name": "Helio H-250 Courier/H-295/395 Super Courier",
      "updated": "2015-10-05T20:27:42.000Z"
    },
    {
      "code": "HS7",
      "name": "British Aerospace/Hawker Siddeley HS748",
      "updated": "2015-10-05T20:27:42.000Z"
    },
    {
      "code": "I14",
      "name": "Ilyushin IL-114",
      "updated": "2015-10-05T20:27:42.000Z"
    },
    {
      "code": "I93",
      "name": "Ilyushin IL-96-300",
      "updated": "2015-10-05T20:27:42.000Z"
    },
    {
      "code": "I9F",
      "name": "Ilyushin IL-96 Freighter",
      "updated": "2015-10-05T20:27:42.000Z"
    },
    {
      "code": "I9M",
      "name": "Ilyushin IL-96M",
      "updated": "2015-10-05T20:27:42.000Z"
    },
    {
      "code": "I9Y",
      "name": "Ilyushin IL-96T",
      "updated": "2015-10-05T20:27:42.000Z"
    },
    {
      "code": "IL6",
      "name": "Ilyushin IL-62",
      "updated": "2015-10-05T20:27:42.000Z"
    },
    {
      "code": "IL7",
      "name": "Ilyushin IL-76",
      "updated": "2015-10-05T20:27:42.000Z"
    },
    {
      "code": "IL8",
      "name": "Ilyushin IL-18",
      "updated": "2015-10-05T20:27:42.000Z"
    },
    {
      "code": "IL9",
      "name": "Ilyushin IL-96",
      "updated": "2015-10-05T20:27:42.000Z"
    },
    {
      "code": "ILW",
      "name": "Ilyushin IL-86",
      "updated": "2015-10-05T20:27:42.000Z"
    },
    {
      "code": "J31",
      "name": "British Aerospace Jetstream 31",
      "updated": "2015-10-05T20:27:42.000Z"
    },
    {
      "code": "J32",
      "name": "British Aerospace Jetstream 32",
      "updated": "2015-10-05T20:27:42.000Z"
    },
    {
      "code": "J41",
      "name": "British Aerospace Jetstream 41",
      "updated": "2015-10-05T20:27:42.000Z"
    },
    {
      "code": "JST",
      "name": "British Aerospace Jetstream 31/32/41",
      "updated": "2015-10-05T20:27:42.000Z"
    },
    {
      "code": "JU5",
      "name": "Junkers Ju52",
      "updated": "2015-10-05T20:27:42.000Z"
    },
    {
      "code": "L10",
      "name": "Lockheed L-1011 Tristar",
      "updated": "2015-10-05T20:27:42.000Z"
    },
    {
      "code": "L11",
      "name": "Lockheed L-1011-1/50/100/150/200/250",
      "updated": "2015-10-05T20:27:42.000Z"
    },
    {
      "code": "L15",
      "name": "Lockheed L-1011-500 Tristar",
      "updated": "2015-10-05T20:27:42.000Z"
    },
    {
      "code": "L1F",
      "name": "Lockheed L-1011 Tristar Freighter",
      "updated": "2015-10-05T20:27:42.000Z"
    },
    {
      "code": "L4T",
      "name": "Let 410 Turbolet",
      "updated": "2015-10-05T20:27:42.000Z"
    },
    {
      "code": "LCH",
      "name": "Non Aircraft - Launch/Boat",
      "updated": "2015-10-05T20:27:42.000Z"
    },
    {
      "code": "LMO",
      "name": "Non Aircraft - Limousine",
      "updated": "2015-10-05T20:27:42.000Z"
    },
    {
      "code": "LOE",
      "name": "Lockheed L-188 Electra",
      "updated": "2015-10-05T20:27:42.000Z"
    },
    {
      "code": "LOH",
      "name": "Lockheed L-100 Hercules",
      "updated": "2015-10-05T20:27:42.000Z"
    },
    { "code": "LRJ", "name": "Learjet", "updated": "2015-10-05T20:27:42.000Z" },
    {
      "code": "M11",
      "name": "Boeing/McDonnell Douglas MD-11",
      "updated": "2015-10-05T20:27:42.000Z"
    },
    {
      "code": "M1F",
      "name": "Boeing/McDonnell Douglas MD-11 Freighter",
      "updated": "2015-10-05T20:27:42.000Z"
    },
    {
      "code": "M1M",
      "name": "Boeing/McDonnell Douglas MD-11 Combi",
      "updated": "2015-10-05T20:27:42.000Z"
    },
    {
      "code": "M80",
      "name": "Boeing/McDonnell Douglas MD-80",
      "updated": "2015-10-05T20:27:42.000Z"
    },
    {
      "code": "M81",
      "name": "Boeing/McDonnell Douglas MD-81",
      "updated": "2015-10-05T20:27:42.000Z"
    },
    {
      "code": "M82",
      "name": "Boeing/McDonnell Douglas MD-82",
      "updated": "2015-10-05T20:27:42.000Z"
    },
    {
      "code": "M83",
      "name": "Boeing/McDonnell Douglas MD-83",
      "updated": "2015-10-05T20:27:42.000Z"
    },
    {
      "code": "M87",
      "name": "Boeing/McDonnell Douglas MD-87",
      "updated": "2015-10-05T20:27:42.000Z"
    },
    {
      "code": "M88",
      "name": "Boeing/McDonnell Douglas MD-88",
      "updated": "2015-10-05T20:27:42.000Z"
    },
    {
      "code": "M90",
      "name": "Boeing/McDonnell Douglas MD-90",
      "updated": "2015-10-05T20:27:42.000Z"
    },
    { "code": "MIH", "name": "Mil", "updated": "2015-10-05T20:27:42.000Z" },
    {
      "code": "MU2",
      "name": "Mitsubishi MU-2",
      "updated": "2015-10-05T20:27:42.000Z"
    },
    {
      "code": "ND2",
      "name": "Aerospatiale/Nord 262",
      "updated": "2015-10-05T20:27:42.000Z"
    },
    {
      "code": "NDC",
      "name": "Aerospatiale SN601 Corvette",
      "updated": "2015-10-05T20:27:42.000Z"
    },
    {
      "code": "NDE",
      "name": "Aerospatiale/Eurocopter Ecureuil AS350/AS355",
      "updated": "2015-10-05T20:27:42.000Z"
    },
    {
      "code": "PA1",
      "name": "Piper light aircraft - single piston engine",
      "updated": "2015-10-05T20:27:42.000Z"
    },
    {
      "code": "PA2",
      "name": "Piper light aircraft - twin piston engines",
      "updated": "2015-10-05T20:27:42.000Z"
    },
    {
      "code": "PAG",
      "name": "Piper Light Aircraft",
      "updated": "2015-10-05T20:27:42.000Z"
    },
    {
      "code": "PL2",
      "name": "Pilatus PC-12",
      "updated": "2015-10-05T20:27:42.000Z"
    },
    {
      "code": "PN6",
      "name": "Partenavia P68",
      "updated": "2015-10-05T20:27:42.000Z"
    },
    {
      "code": "S20",
      "name": "Saab 2000",
      "updated": "2015-10-05T20:27:42.000Z"
    },
    {
      "code": "S58",
      "name": "Sikorsky S-58T",
      "updated": "2015-10-05T20:27:42.000Z"
    },
    {
      "code": "S61",
      "name": "Sikorsky S-61",
      "updated": "2015-10-05T20:27:42.000Z"
    },
    {
      "code": "S76",
      "name": "Sikorsky S-76",
      "updated": "2015-10-05T20:27:42.000Z"
    },
    {
      "code": "SF3",
      "name": "Saab SF-340",
      "updated": "2015-10-05T20:27:42.000Z"
    },
    {
      "code": "SFB",
      "name": "Saab SF-340B",
      "updated": "2015-10-05T20:27:42.000Z"
    },
    {
      "code": "SH3",
      "name": "Shorts SD-330",
      "updated": "2015-10-05T20:27:42.000Z"
    },
    {
      "code": "SH6",
      "name": "Shorts SD-360",
      "updated": "2015-10-05T20:27:42.000Z"
    },
    {
      "code": "SSC",
      "name": "Aerospatiale/British Aerospace Concorde (discontinued)",
      "updated": "2015-10-05T20:27:42.000Z"
    },
    {
      "code": "SWM",
      "name": "Fairchild Metro/Merlin",
      "updated": "2015-10-05T20:27:42.000Z"
    },
    {
      "code": "T20",
      "name": "Tupolev Tu-204/214",
      "updated": "2015-10-05T20:27:42.000Z"
    },
    {
      "code": "TRN",
      "name": "Non Aircraft - Train",
      "updated": "2015-10-05T20:27:42.000Z"
    },
    {
      "code": "TU3",
      "name": "Tupolev Tu-134",
      "updated": "2015-10-05T20:27:42.000Z"
    },
    {
      "code": "TU5",
      "name": "Tupolev Tu-154",
      "updated": "2015-10-05T20:27:42.000Z"
    },
    {
      "code": "VCV",
      "name": "Vickers Viscount",
      "updated": "2015-10-05T20:27:42.000Z"
    },
    {
      "code": "WWP",
      "name": "Israel Aircraft Industries 1124 Westwind",
      "updated": "2015-10-05T20:27:42.000Z"
    },
    {
      "code": "YK2",
      "name": "Yakovlev Yak-42",
      "updated": "2015-10-05T20:27:42.000Z"
    },
    {
      "code": "YK4",
      "name": "Yakovlev Yak-40",
      "updated": "2015-10-05T20:27:42.000Z"
    },
    {
      "code": "YN2",
      "name": "Yunshuji Y-12/Xian Y-12",
      "updated": "2015-10-05T20:27:42.000Z"
    },
    {
      "code": "YN7",
      "name": "Yunshuji Y-7/Harbin Y-7",
      "updated": "2015-10-05T20:27:42.000Z"
    },
    {
      "code": "YS1",
      "name": "NAMC YS-11",
      "updated": "2015-10-05T20:27:42.000Z"
    }
  ]
}
